unique_char_counter_cli_kir_boh/__init__.py
unique_char_counter_cli_kir_boh/unique_char_counter_cli.py
unique_char_counter_cli_kir_boh/tests/__init__.py
unique_char_counter_cli_kir_boh/tests/test_unique_char_counter_cli.py
unique_char_counter_cli_kir_boh/tests/.pytest_cache/.gitignore
unique_char_counter_cli_kir_boh/tests/.pytest_cache/CACHEDIR.TAG
unique_char_counter_cli_kir_boh/tests/.pytest_cache/README.md
unique_char_counter_cli_kir_boh/tests/.pytest_cache/v/cache/lastfailed
unique_char_counter_cli_kir_boh/tests/.pytest_cache/v/cache/nodeids
unique_char_counter_cli_kir_boh/tests/.pytest_cache/v/cache/stepwise
unique_char_counter_cli_kir_boh-2.1.dist-info/METADATA
unique_char_counter_cli_kir_boh-2.1.dist-info/WHEEL
unique_char_counter_cli_kir_boh-2.1.dist-info/licenses/LICENSE
unique_char_counter_cli_kir_boh-2.1.dist-info/RECORD
