Metadata-Version: 2.1
Name: unique_char_counter_cli_kir_boh
Version: 2.1
Summary: Project gets hashable obj from cli an returns uniqe items amount, other funcs desribed in README.md
Author-email: Kiril Bogatiuk <kirillbogatu2005@gmail.com>
Maintainer-email: Stanislav Hrytsyshyn <NeZnavVashMail@gmail.com>
License-File: LICENSE
Classifier: License :: OSI Approved :: MIT License
Classifier: Operating System :: OS Independent
Classifier: Programming Language :: Python :: 3
Requires-Python: >=3.7
